Workbook
Name Slicer_Region: #N/A

Sheet Dashboard

Sheet CustomerSummary
A1: Customer ID | B1: Customer Name | C1: Total Purchase (Sales) | D1: Total Profit | E1: Order Count | F1: Rank | G1: Top 10? | I1: Top Rank | J1: High-Value Customer
A2: CUST001 | B2: Jordan Smith | C2: =SUMIFS(DATA!E:E, DATA!A:A, A2) -> 621.5 | D2: =SUMIFS(DATA!J:J, DATA!A:A, A2) -> 157.49 | E2: =COUNTIF(DATA!A:A, A2) -> 1 | F2: =RANK(C2, C:C) -> 53 | G2: =IF(F2<=10, "Yes", "No") -> No | I2: 1 | J2: =INDEX(B:B, MATCH(I2, F:F, 0)) -> Riley Martinez
A3: CUST002 | B3: Casey Brown | C3: =SUMIFS(DATA!E:E, DATA!A:A, A3) -> 348.85 | D3: =SUMIFS(DATA!J:J, DATA!A:A, A3) -> 75.64 | E3: =COUNTIF(DATA!A:A, A3) -> 1 | F3: =RANK(C3, C:C) -> 71 | G3: =IF(F3<=10, "Yes", "No") -> No | I3: 2 | J3: =INDEX(B:B, MATCH(I3, F:F, 0)) -> Skyler Miller
A4: CUST003 | B4: Morgan Williams | C4: =SUMIFS(DATA!E:E, DATA!A:A, A4) -> 706.32 | D4: =SUMIFS(DATA!J:J, DATA!A:A, A4) -> 128.78 | E4: =COUNTIF(DATA!A:A, A4) -> 1 | F4: =RANK(C4, C:C) -> 46 | G4: =IF(F4<=10, "Yes", "No") -> No | I4: 3 | J4: =INDEX(B:B, MATCH(I4, F:F, 0)) -> Alex Garcia
A5: CUST004 | B5: Jordan Rodriguez | C5: =SUMIFS(DATA!E:E, DATA!A:A, A5) -> 1468.41 | D5: =SUMIFS(DATA!J:J, DATA!A:A, A5) -> 410.73 | E5: =COUNTIF(DATA!A:A, A5) -> 1 | F5: =RANK(C5, C:C) -> 19 | G5: =IF(F5<=10, "Yes", "No") -> No | I5: 4 | J5: =INDEX(B:B, MATCH(I5, F:F, 0)) -> Riley Williams
A6: CUST005 | B6: Jordan Martinez | C6: =SUMIFS(DATA!E:E, DATA!A:A, A6) -> 126.64 | D6: =SUMIFS(DATA!J:J, DATA!A:A, A6) -> 31.19 | E6: =COUNTIF(DATA!A:A, A6) -> 1 | F6: =RANK(C6, C:C) -> 84 | G6: =IF(F6<=10, "Yes", "No") -> No | I6: 5 | J6: =INDEX(B:B, MATCH(I6, F:F, 0)) -> Morgan Jones
A7: CUST006 | B7: Jamie Smith | C7: =SUMIFS(DATA!E:E, DATA!A:A, A7) -> 201.14 | D7: =SUMIFS(DATA!J:J, DATA!A:A, A7) -> 30.54 | E7: =COUNTIF(DATA!A:A, A7) -> 1 | F7: =RANK(C7, C:C) -> 73 | G7: =IF(F7<=10, "Yes", "No") -> No | I7: 6 | J7: =INDEX(B:B, MATCH(I7, F:F, 0)) -> Cameron Rodriguez
A8: CUST007 | B8: Alex Johnson | C8: =SUMIFS(DATA!E:E, DATA!A:A, A8) -> 116.23 | D8: =SUMIFS(DATA!J:J, DATA!A:A, A8) -> 16.89 | E8: =COUNTIF(DATA!A:A, A8) -> 1 | F8: =RANK(C8, C:C) -> 85 | G8: =IF(F8<=10, "Yes", "No") -> No | I8: 7 | J8: =INDEX(B:B, MATCH(I8, F:F, 0)) -> Morgan Martinez
A9: CUST008 | B9: Morgan Brown | C9: =SUMIFS(DATA!E:E, DATA!A:A, A9) -> 480.81 | D9: =SUMIFS(DATA!J:J, DATA!A:A, A9) -> 111.88 | E9: =COUNTIF(DATA!A:A, A9) -> 1 | F9: =RANK(C9, C:C) -> 58 | G9: =IF(F9<=10, "Yes", "No") -> No | I9: 8 | J9: =INDEX(B:B, MATCH(I9, F:F, 0)) -> Skyler Johnson
A10: CUST009 | B10: Cameron Martinez | C10: =SUMIFS(DATA!E:E, DATA!A:A, A10) -> 1632.36 | D10: =SUMIFS(DATA!J:J, DATA!A:A, A10) -> 328.12 | E10: =COUNTIF(DATA!A:A, A10) -> 1 | F10: =RANK(C10, C:C) -> 16 | G10: =IF(F10<=10, "Yes", "No") -> No | I10: 9 | J10: =INDEX(B:B, MATCH(I10, F:F, 0)) -> Riley Miller
A11: CUST010 | B11: Alex Rodriguez | C11: =SUMIFS(DATA!E:E, DATA!A:A, A11) -> 666.63 | D11: =SUMIFS(DATA!J:J, DATA!A:A, A11) -> 88.1 | E11: =COUNTIF(DATA!A:A, A11) -> 1 | F11: =RANK(C11, C:C) -> 48 | G11: =IF(F11<=10, "Yes", "No") -> No | I11: 10 | J11: =INDEX(B:B, MATCH(I11, F:F, 0)) -> Taylor Smith
A12: CUST011 | B12: Morgan Rodriguez | C12: =SUMIFS(DATA!E:E, DATA!A:A, A12) -> 1808.23 | D12: =SUMIFS(DATA!J:J, DATA!A:A, A12) -> 560.09 | E12: =COUNTIF(DATA!A:A, A12) -> 1 | F12: =RANK(C12, C:C) -> 12 | G12: =IF(F12<=10, "Yes", "No") -> No
A13: CUST012 | B13: Jamie Brown | C13: =SUMIFS(DATA!E:E, DATA!A:A, A13) -> 415.71 | D13: =SUMIFS(DATA!J:J, DATA!A:A, A13) -> 130.27 | E13: =COUNTIF(DATA!A:A, A13) -> 1 | F13: =RANK(C13, C:C) -> 66 | G13: =IF(F13<=10, "Yes", "No") -> No
A14: CUST013 | B14: Skyler Martinez | C14: =SUMIFS(DATA!E:E, DATA!A:A, A14) -> 239.96 | D14: =SUMIFS(DATA!J:J, DATA!A:A, A14) -> 67.28 | E14: =COUNTIF(DATA!A:A, A14) -> 1 | F14: =RANK(C14, C:C) -> 72 | G14: =IF(F14<=10, "Yes", "No") -> No
A15: CUST014 | B15: Casey Smith | C15: =SUMIFS(DATA!E:E, DATA!A:A, A15) -> 537.21 | D15: =SUMIFS(DATA!J:J, DATA!A:A, A15) -> 118.11 | E15: =COUNTIF(DATA!A:A, A15) -> 1 | F15: =RANK(C15, C:C) -> 55 | G15: =IF(F15<=10, "Yes", "No") -> No
A16: CUST015 | B16: Taylor Miller | C16: =SUMIFS(DATA!E:E, DATA!A:A, A16) -> 374.55 | D16: =SUMIFS(DATA!J:J, DATA!A:A, A16) -> 128.26 | E16: =COUNTIF(DATA!A:A, A16) -> 1 | F16: =RANK(C16, C:C) -> 68 | G16: =IF(F16<=10, "Yes", "No") -> No
A17: CUST016 | B17: Riley Jones | C17: =SUMIFS(DATA!E:E, DATA!A:A, A17) -> 597.13 | D17: =SUMIFS(DATA!J:J, DATA!A:A, A17) -> 102.97 | E17: =COUNTIF(DATA!A:A, A17) -> 1 | F17: =RANK(C17, C:C) -> 54 | G17: =IF(F17<=10, "Yes", "No") -> No
A18: CUST017 | B18: Taylor Brown | C18: =SUMIFS(DATA!E:E, DATA!A:A, A18) -> 1153.02 | D18: =SUMIFS(DATA!J:J, DATA!A:A, A18) -> 305.64 | E18: =COUNTIF(DATA!A:A, A18) -> 1 | F18: =RANK(C18, C:C) -> 28 | G18: =IF(F18<=10, "Yes", "No") -> No
A19: CUST018 | B19: Riley Johnson | C19: =SUMIFS(DATA!E:E, DATA!A:A, A19) -> 160.79 | D19: =SUMIFS(DATA!J:J, DATA!A:A, A19) -> 56.16 | E19: =COUNTIF(DATA!A:A, A19) -> 1 | F19: =RANK(C19, C:C) -> 77 | G19: =IF(F19<=10, "Yes", "No") -> No
A20: CUST019 | B20: Jordan Miller | C20: =SUMIFS(DATA!E:E, DATA!A:A, A20) -> 838.43 | D20: =SUMIFS(DATA!J:J, DATA!A:A, A20) -> 213.74 | E20: =COUNTIF(DATA!A:A, A20) -> 1 | F20: =RANK(C20, C:C) -> 40 | G20: =IF(F20<=10, "Yes", "No") -> No
A21: CUST020 | B21: Jordan Garcia | C21: =SUMIFS(DATA!E:E, DATA!A:A, A21) -> 364.13 | D21: =SUMIFS(DATA!J:J, DATA!A:A, A21) -> 125.57 | E21: =COUNTIF(DATA!A:A, A21) -> 1 | F21: =RANK(C21, C:C) -> 70 | G21: =IF(F21<=10, "Yes", "No") -> No
A22: CUST021 | B22: Riley Martinez | C22: =SUMIFS(DATA!E:E, DATA!A:A, A22) -> 2300.33 | D22: =SUMIFS(DATA!J:J, DATA!A:A, A22) -> 647.59 | E22: =COUNTIF(DATA!A:A, A22) -> 1 | F22: =RANK(C22, C:C) -> 1 | G22: =IF(F22<=10, "Yes", "No") -> Yes
A23: CUST023 | B23: Skyler Rodriguez | C23: =SUMIFS(DATA!E:E, DATA!A:A, A23) -> 1341.8 | D23: =SUMIFS(DATA!J:J, DATA!A:A, A23) -> 293.5 | E23: =COUNTIF(DATA!A:A, A23) -> 1 | F23: =RANK(C23, C:C) -> 23 | G23: =IF(F23<=10, "Yes", "No") -> No
... A89: CUST199 | B89: Riley Rodriguez | C89: =SUMIFS(DATA!E:E, DATA!A:A, A89) -> 1228.26 | D89: =SUMIFS(DATA!J:J, DATA!A:A, A89) -> 399.4 | E89: =COUNTIF(DATA!A:A, A89) -> 1 | F89: =RANK(C89, C:C) -> 26 | G89: =IF(F89<=10, "Yes", "No") -> No

Sheet MonthlySales
A2: Month | B2: Total Sales | C2: Total Profit | D2: Growth vs Prior Month
A3: 46023 | B3: =SUMIFS(DATA!E:E, DATA!K:K, A3) -> 37627.84 | C3: =SUMIFS(DATA!J:J, DATA!K:K, A3) -> 9727.01 | D3: =(B4-B3)/B3 -> -0.28839258
A4: 46054 | B4: =SUMIFS(DATA!E:E, DATA!K:K, A4) -> 26776.25 | C4: =SUMIFS(DATA!J:J, DATA!K:K, A4) -> 6625.67 | D4: =(B5-B4)/B4 -> -0.16852995
A5: 46082 | B5: =SUMIFS(DATA!E:E, DATA!K:K, A5) -> 22263.65 | C5: =SUMIFS(DATA!J:J, DATA!K:K, A5) -> 5812.65 | D5: =(B6-B5)/B5 -> 0.37821202
A6: 46113 | B6: =SUMIFS(DATA!E:E, DATA!K:K, A6) -> 30684.03 | C6: =SUMIFS(DATA!J:J, DATA!K:K, A6) -> 7413.04 | D6: =(B7-B6)/B6 -> -0.1917724
A7: 46143 | B7: =SUMIFS(DATA!E:E, DATA!K:K, A7) -> 24799.68 | C7: =SUMIFS(DATA!J:J, DATA!K:K, A7) -> 6380.2 | D7: =(B8-B7)/B7 -> 0.36339743
A8: 46174 | B8: =SUMIFS(DATA!E:E, DATA!K:K, A8) -> 33811.82 | C8: =SUMIFS(DATA!J:J, DATA!K:K, A8) -> 8429.62 | D8: =(B9-B8)/B8 -> -1

Sheet PivotTable
A3: TOTAL SALES BY REGION AND PRODUCT | B3: Region
A4: Product Category | B4: Central | C4: East | D4: North | E4: South | F4: West | G4: Grand Total
A5: Security Cameras | B5: 18808.8 | C5: 11773.11 | D5: 7922.61 | E5: 10421.83 | F5: 15002.63 | G5: 63928.98
A6: Smart Lighting | B6: 2247.4 | C6: 4114.23 | D6: 3187.23 | E6: 3711.09 | F6: 6619.84 | G6: 19879.79
A7: Smart Speakers | B7: 8483.54 | C7: 5953.99 | D7: 5613.81 | E7: 8785.27 | F7: 9298.25 | G7: 38134.86
A8: Smart Thermostats | B8: 7512.13 | C8: 14688.6 | D8: 7338.86 | E8: 14302.49 | F8: 10177.56 | G8: 54019.64
A9: Grand Total | B9: 37051.87 | C9: 36529.93 | D9: 24062.51 | E9: 37220.68 | F9: 41098.28 | G9: 175963.27

Sheet WhatIf
B1: Scenario Analysis: Discount Impact Model
B2: Adjust the highlighted input cell below to forecast how changing the average discount rate impacts overall company profitability
B3: Average Current Discount | C3: =AVERAGE(DATA!G:G) -> 0.09725 | E3: New Proposed Discount | F3: 0.1
B4: Total Current Sales | C4: =SUM(DATA!E:E) -> 175963.27 | E4: Total Profit at New Discount | F4: =(C4/(1-C3)) * (1-F3) * (AVERAGE(DATA!J:J)/AVERAGE(DATA!E:E)) -> 44252.973

Sheet DescriptiveStats
A2: Column1 | B2: Column2 | C2: Column3 | D2: Column4 | E2: Column5 | F2: Column6
A3: Mean | B3: 879.81635 | C3: Mean | D3: 5.735 | E3: Mean | F3: 0.09725
A4: Standard Error | B4: 41.580709 | C4: Standard Error | D4: 0.20018553 | E4: Standard Error | F4: 0.0048494612
A5: Median | B5: 741.86 | C5: Median | D5: 6 | E5: Median | F5: 0.1
A6: Mode | B6: #N/A | C6: Mode | D6: 8 | E6: Mode | F6: 0.1
A7: Standard Deviation | B7: 588.04002 | C7: Standard Deviation | D7: 2.8310509 | E7: Standard Deviation | F7: 0.068581738
A8: Sample Variance | B8: 345791.07 | C8: Sample Variance | D8: 8.0148492 | E8: Sample Variance | F8: 0.0047034548
A9: Kurtosis | B9: -0.64754673 | C9: Kurtosis | D9: -1.2168786 | E9: Kurtosis | F9: -1.2068501
A10: Skewness | B10: 0.59792483 | C10: Skewness | D10: -0.16359034 | E10: Skewness | F10: 0.0055241184
A11: Range | B11: 2231.69 | C11: Range | D11: 9 | E11: Range | F11: 0.2
A12: Minimum | B12: 68.64 | C12: Minimum | D12: 1 | E12: Minimum | F12: 0
A13: Maximum | B13: 2300.33 | C13: Maximum | D13: 10 | E13: Maximum | F13: 0.2
A14: Sum | B14: 175963.27 | C14: Sum | D14: 1147 | E14: Sum | F14: 19.45
A15: Count | B15: 200 | C15: Count | D15: 200 | E15: Count | F15: 200

Sheet Regression
A3: Regression Statistics | B3: Column1
A4: Multiple R | B4: 0.91337618
A5: R Square | B5: 0.83425604
A6: Adjusted R Square | B6: 0.83341895
A7: Standard Error | B7: 67.466403
A8: Observations | B8: 200
A10: ANOVA | B10: Column1 | C10: Column2 | D10: Column3 | E10: Column4 | F10: Column5
B11: df | C11: SS | D11: MS | E11: F | F11: Significance F
A12: Regression | B12: 1 | C12: 4536302 | D12: 4536302 | E12: 996.61368 | F12: 3.2833114e-79
A13: Residual | B13: 198 | C13: 901239.68 | D13: 4551.7155
A14: Total | B14: 199 | C14: 5437541.6
A16: Column1 | B16: Coefficients | C16: Standard Error | D16: t Stat | E16: P-value | F16: Lower 95% | G16: Upper 95% | H16: Lower 95.0% | I16: Upper 95.0%
A17: Intercept | B17: -3.9555913 | C17: 8.6000706 | D17: -0.4599487 | E17: 0.6460577 | F17: -20.915081 | G17: 13.003898 | H17: -20.915081 | I17: 13.003898
A18: X Variable 1 | B18: 0.2567542 | C18: 0.0081330629 | D18: 31.569189 | E18: 3.2833114e-79 | F18: 0.24071566 | G18: 0.27279274 | H18: 0.24071566 | I18: 0.27279274

Sheet DATA
A1: Customer_ID | B1: Customer_Name | C1: Region | D1: Product_Category | E1: Sales | F1: Quantity | G1: Discount | H1: Order_Date | I1: Month | J1: Profit | K1: Order Month. | L1: Timestamp
A2: CUST001 | B2: Jordan Smith | C2: South | D2: Security Cameras | E2: 621.5 | F2: 3 | G2: 0.15 | H2: 2026-02-22 | I2: 2 | J2: 157.49 | K2: =EOMONTH(H2, -1) + 1 -> 46054 | L2: =NOW() -> 46278.541
A3: CUST002 | B3: Casey Brown | C3: South | D3: Smart Lighting | E3: 348.85 | F3: 4 | G3: 0 | H3: 2026-01-18 | I3: 1 | J3: 75.64 | K3: =EOMONTH(H3, -1) + 1 -> 46023 | L3: =NOW() -> 46278.541
A4: CUST003 | B4: Morgan Williams | C4: South | D4: Security Cameras | E4: 706.32 | F4: 3 | G4: 0.1 | H4: 2026-05-22 | I4: 5 | J4: 128.78 | K4: =EOMONTH(H4, -1) + 1 -> 46143 | L4: =NOW() -> 46278.541
A5: CUST004 | B5: Jordan Rodriguez | C5: South | D5: Smart Thermostats | E5: 1468.41 | F5: 9 | G5: 0.2 | H5: 2026-02-23 | I5: 2 | J5: 410.73 | K5: =EOMONTH(H5, -1) + 1 -> 46054 | L5: =NOW() -> 46278.541
A6: CUST005 | B6: Jordan Martinez | C6: West | D6: Smart Lighting | E6: 126.64 | F6: 2 | G6: 0.15 | H6: 2026-05-31 | I6: 5 | J6: 31.19 | K6: =EOMONTH(H6, -1) + 1 -> 46143 | L6: =NOW() -> 46278.541
A7: CUST006 | B7: Jamie Smith | C7: North | D7: Smart Lighting | E7: 201.14 | F7: 3 | G7: 0.1 | H7: 2026-02-25 | I7: 2 | J7: 30.54 | K7: =EOMONTH(H7, -1) + 1 -> 46054 | L7: =NOW() -> 46278.541
A8: CUST007 | B8: Alex Johnson | C8: South | D8: Smart Speakers | E8: 116.23 | F8: 1 | G8: 0.15 | H8: 2026-03-01 | I8: 3 | J8: 16.89 | K8: =EOMONTH(H8, -1) + 1 -> 46082 | L8: =NOW() -> 46278.541
A9: CUST008 | B9: Morgan Brown | C9: East | D9: Smart Lighting | E9: 480.81 | F9: 7 | G9: 0.2 | H9: 2026-03-26 | I9: 3 | J9: 111.88 | K9: =EOMONTH(H9, -1) + 1 -> 46082 | L9: =NOW() -> 46278.541
A10: CUST009 | B10: Cameron Martinez | C10: West | D10: Smart Thermostats | E10: 1632.36 | F10: 8 | G10: 0 | H10: 2026-02-07 | I10: 2 | J10: 328.12 | K10: =EOMONTH(H10, -1) + 1 -> 46054 | L10: =NOW() -> 46278.541
A11: CUST010 | B11: Alex Rodriguez | C11: South | D11: Smart Lighting | E11: 666.63 | F11: 10 | G11: 0.2 | H11: 2026-06-02 | I11: 6 | J11: 88.1 | K11: =EOMONTH(H11, -1) + 1 -> 46174 | L11: =NOW() -> 46278.541
A12: CUST011 | B12: Morgan Rodriguez | C12: East | D12: Security Cameras | E12: 1808.23 | F12: 8 | G12: 0 | H12: 2026-01-01 | I12: 1 | J12: 560.09 | K12: =EOMONTH(H12, -1) + 1 -> 46023 | L12: =NOW() -> 46278.541
A13: CUST012 | B13: Jamie Brown | C13: South | D13: Smart Lighting | E13: 415.71 | F13: 5 | G13: 0.05 | H13: 2026-03-12 | I13: 3 | J13: 130.27 | K13: =EOMONTH(H13, -1) + 1 -> 46082 | L13: =NOW() -> 46278.541
... A201: CUST200 | B201: Jamie Martinez | C201: Central | D201: Smart Speakers | E201: 1267.17 | F201: 10 | G201: 0.2 | H201: 2026-06-19 | I201: 6 | J201: 317.94 | K201: =EOMONTH(H201, -1) + 1 -> 46174 | L201: =NOW() -> 46278.541
