Workbook

Sheet Students grade
A1: Student ID | B1: Full Name | C1: DOB | D1: Math | E1: Science | F1: Average | G1: Grade | H1: Above 80 in Both | I1: First Name | J1: Name (Upper) | K1: Name (Lower) | L1: age
A2: 1 | B2: Ishita Rathod | C2: 38902 | D2: 87 | E2: 90 | F2: =AVERAGE(D2:E2) -> 88.5 | G2: =IF(OR(D2<35,E2<35),"F",IF(AVERAGE(D2:E2)>=90,"A",IF(AVERAGE(D2:E2)>=75,"B",IF(AVERAGE(D2:E2)>=60,"C",IF(AVERAGE(D2:E2)>=50,"D","F"))))) -> B | H2: =IF(AND(D2>80,E2>80),"YES","NO") -> YES | I2: =LEFT(B2,FIND(" ",B2)-1) -> Ishita | J2: =UPPER(I2) -> ISHITA | K2: =LOWER(I2) -> ishita | L2: =DATEDIF(C2, TODAY(), "y") -> 20
A3: 2 | B3: Ishaan Solanki | C3: 39471 | D3: 86 | E3: 96 | F3: =AVERAGE(D3:E3) -> 91 | G3: =IF(OR(D3<35,E3<35),"F",IF(AVERAGE(D3:E3)>=90,"A",IF(AVERAGE(D3:E3)>=75,"B",IF(AVERAGE(D3:E3)>=60,"C",IF(AVERAGE(D3:E3)>=50,"D","F"))))) -> A | H3: =IF(AND(D3>80,E3>80),"YES","NO") -> YES | I3: =LEFT(B3,FIND(" ",B3)-1) -> Ishaan | J3: =UPPER(I3) -> ISHAAN | K3: =LOWER(I3) -> ishaan | L3: =DATEDIF(C3, TODAY(), "y") -> 18
A4: 3 | B4: Meera Kapoor | C4: 38901 | D4: 98 | E4: 65 | F4: =AVERAGE(D4:E4) -> 81.5 | G4: =IF(OR(D4<35,E4<35),"F",IF(AVERAGE(D4:E4)>=90,"A",IF(AVERAGE(D4:E4)>=75,"B",IF(AVERAGE(D4:E4)>=60,"C",IF(AVERAGE(D4:E4)>=50,"D","F"))))) -> B | H4: =IF(AND(D4>80,E4>80),"YES","NO") -> NO | I4: =LEFT(B4,FIND(" ",B4)-1) -> Meera | J4: =UPPER(I4) -> MEERA | K4: =LOWER(I4) -> meera | L4: =DATEDIF(C4, TODAY(), "y") -> 20
A5: 4 | B5: Ritika Bhatt | C5: 39728 | D5: 87 | E5: 89 | F5: =AVERAGE(D5:E5) -> 88 | G5: =IF(OR(D5<35,E5<35),"F",IF(AVERAGE(D5:E5)>=90,"A",IF(AVERAGE(D5:E5)>=75,"B",IF(AVERAGE(D5:E5)>=60,"C",IF(AVERAGE(D5:E5)>=50,"D","F"))))) -> B | H5: =IF(AND(D5>80,E5>80),"YES","NO") -> YES | I5: =LEFT(B5,FIND(" ",B5)-1) -> Ritika | J5: =UPPER(I5) -> RITIKA | K5: =LOWER(I5) -> ritika | L5: =DATEDIF(C5, TODAY(), "y") -> 17
A6: 5 | B6: Kavya Chauhan | C6: 39205 | D6: 57 | E6: 40 | F6: =AVERAGE(D6:E6) -> 48.5 | G6: =IF(OR(D6<35,E6<35),"F",IF(AVERAGE(D6:E6)>=90,"A",IF(AVERAGE(D6:E6)>=75,"B",IF(AVERAGE(D6:E6)>=60,"C",IF(AVERAGE(D6:E6)>=50,"D","F"))))) -> F | H6: =IF(AND(D6>80,E6>80),"YES","NO") -> NO | I6: =LEFT(B6,FIND(" ",B6)-1) -> Kavya | J6: =UPPER(I6) -> KAVYA | K6: =LOWER(I6) -> kavya | L6: =DATEDIF(C6, TODAY(), "y") -> 19
A7: 6 | B7: Siddharth Trivedi | C7: 39948 | D7: 74 | E7: 48 | F7: =AVERAGE(D7:E7) -> 61 | G7: =IF(OR(D7<35,E7<35),"F",IF(AVERAGE(D7:E7)>=90,"A",IF(AVERAGE(D7:E7)>=75,"B",IF(AVERAGE(D7:E7)>=60,"C",IF(AVERAGE(D7:E7)>=50,"D","F"))))) -> C | H7: =IF(AND(D7>80,E7>80),"YES","NO") -> NO | I7: =LEFT(B7,FIND(" ",B7)-1) -> Siddharth | J7: =UPPER(I7) -> SIDDHARTH | K7: =LOWER(I7) -> siddharth | L7: =DATEDIF(C7, TODAY(), "y") -> 17
A8: 7 | B8: Tanvi Nair | C8: 39606 | D8: 96 | E8: 90 | F8: =AVERAGE(D8:E8) -> 93 | G8: =IF(OR(D8<35,E8<35),"F",IF(AVERAGE(D8:E8)>=90,"A",IF(AVERAGE(D8:E8)>=75,"B",IF(AVERAGE(D8:E8)>=60,"C",IF(AVERAGE(D8:E8)>=50,"D","F"))))) -> A | H8: =IF(AND(D8>80,E8>80),"YES","NO") -> YES | I8: =LEFT(B8,FIND(" ",B8)-1) -> Tanvi | J8: =UPPER(I8) -> TANVI | K8: =LOWER(I8) -> tanvi | L8: =DATEDIF(C8, TODAY(), "y") -> 18
A9: 8 | B9: Neel Shah | C9: 39349 | D9: 59 | E9: 48 | F9: =AVERAGE(D9:E9) -> 53.5 | G9: =IF(OR(D9<35,E9<35),"F",IF(AVERAGE(D9:E9)>=90,"A",IF(AVERAGE(D9:E9)>=75,"B",IF(AVERAGE(D9:E9)>=60,"C",IF(AVERAGE(D9:E9)>=50,"D","F"))))) -> D | H9: =IF(AND(D9>80,E9>80),"YES","NO") -> NO | I9: =LEFT(B9,FIND(" ",B9)-1) -> Neel | J9: =UPPER(I9) -> NEEL | K9: =LOWER(I9) -> neel | L9: =DATEDIF(C9, TODAY(), "y") -> 18
A10: 9 | B10: Riya Bansal | C10: 40003 | D10: 56 | E10: 69 | F10: =AVERAGE(D10:E10) -> 62.5 | G10: =IF(OR(D10<35,E10<35),"F",IF(AVERAGE(D10:E10)>=90,"A",IF(AVERAGE(D10:E10)>=75,"B",IF(AVERAGE(D10:E10)>=60,"C",IF(AVERAGE(D10:E10)>=50,"D","F"))))) -> C | H10: =IF(AND(D10>80,E10>80),"YES","NO") -> NO | I10: =LEFT(B10,FIND(" ",B10)-1) -> Riya | J10: =UPPER(I10) -> RIYA | K10: =LOWER(I10) -> riya | L10: =DATEDIF(C10, TODAY(), "y") -> 17
A11: 10 | B11: Sneha Deshmukh | C11: 38834 | D11: 96 | E11: 95 | F11: =AVERAGE(D11:E11) -> 95.5 | G11: =IF(OR(D11<35,E11<35),"F",IF(AVERAGE(D11:E11)>=90,"A",IF(AVERAGE(D11:E11)>=75,"B",IF(AVERAGE(D11:E11)>=60,"C",IF(AVERAGE(D11:E11)>=50,"D","F"))))) -> A | H11: =IF(AND(D11>80,E11>80),"YES","NO") -> YES | I11: =LEFT(B11,FIND(" ",B11)-1) -> Sneha | J11: =UPPER(I11) -> SNEHA | K11: =LOWER(I11) -> sneha | L11: =DATEDIF(C11, TODAY(), "y") -> 20
A12: 11 | B12: Rohan Malhotra | C12: 39936 | D12: 55 | E12: 68 | F12: =AVERAGE(D12:E12) -> 61.5 | G12: =IF(OR(D12<35,E12<35),"F",IF(AVERAGE(D12:E12)>=90,"A",IF(AVERAGE(D12:E12)>=75,"B",IF(AVERAGE(D12:E12)>=60,"C",IF(AVERAGE(D12:E12)>=50,"D","F"))))) -> C | H12: =IF(AND(D12>80,E12>80),"YES","NO") -> NO | I12: =LEFT(B12,FIND(" ",B12)-1) -> Rohan | J12: =UPPER(I12) -> ROHAN | K12: =LOWER(I12) -> rohan | L12: =DATEDIF(C12, TODAY(), "y") -> 17
A13: 12 | B13: Ananya Iyer | C13: 39402 | D13: 78 | E13: 86 | F13: =AVERAGE(D13:E13) -> 82 | G13: =IF(OR(D13<35,E13<35),"F",IF(AVERAGE(D13:E13)>=90,"A",IF(AVERAGE(D13:E13)>=75,"B",IF(AVERAGE(D13:E13)>=60,"C",IF(AVERAGE(D13:E13)>=50,"D","F"))))) -> B | H13: =IF(AND(D13>80,E13>80),"YES","NO") -> NO | I13: =LEFT(B13,FIND(" ",B13)-1) -> Ananya | J13: =UPPER(I13) -> ANANYA | K13: =LOWER(I13) -> ananya | L13: =DATEDIF(C13, TODAY(), "y") -> 18

Sheet Sales Data
A1: Sales ID | B1: Region | C1: Product | D1: Product Code | E1: Sales Person | F1: Month | G1: Price | H1: Quantity | I1: Sales Amount | J1: Date | K1: Discount % | L1: Discount Eligible
A2: 1 | B2: West | C2: Keyboard | D2: 103 | E2: Sonal Kapoor | F2: Jan | G2: 1124 | H2: 9 | I2: =G2*H2 -> 10116 | J2: 46078 | K2: =IF(G2>=50000,"15%",IF(G2>=25000,"10%",IF(G2>=10000,"5%",IF(G2>=5000,"2%","0%")))) -> 0% | L2: =IF(OR(G2>=5000,H2>=50),"YES","NO") -> NO
A3: 2 | B3: North | C3: Laptop | D3: 101 | E3: Neha Kulkarni | F3: Feb | G3: 53252 | H3: 41 | I3: =G3*H3 -> 2183332 | J3: 46223 | K3: =IF(G3>=50000,"15%",IF(G3>=25000,"10%",IF(G3>=10000,"5%",IF(G3>=5000,"2%","0%")))) -> 15% | L3: =IF(OR(G3>=5000,H3>=50),"YES","NO") -> YES
A4: 3 | B4: North | C4: Mouse | D4: 104 | E4: Sonal Kapoor | F4: Mar | G4: 545 | H4: 39 | I4: =G4*H4 -> 21255 | J4: 46160 | K4: =IF(G4>=50000,"15%",IF(G4>=25000,"10%",IF(G4>=10000,"5%",IF(G4>=5000,"2%","0%")))) -> 0% | L4: =IF(OR(G4>=5000,H4>=50),"YES","NO") -> NO
A5: 4 | B5: North | C5: Laptop | D5: 101 | E5: Aman Bose | F5: Apr | G5: 57584 | H5: 57 | I5: =G5*H5 -> 3282288 | J5: 46177 | K5: =IF(G5>=50000,"15%",IF(G5>=25000,"10%",IF(G5>=10000,"5%",IF(G5>=5000,"2%","0%")))) -> 15% | L5: =IF(OR(G5>=5000,H5>=50),"YES","NO") -> YES
A6: 5 | B6: East | C6: Mouse | D6: 104 | E6: Rahul Desai | F6: May | G6: 430 | H6: 30 | I6: =G6*H6 -> 12900 | J6: 46159 | K6: =IF(G6>=50000,"15%",IF(G6>=25000,"10%",IF(G6>=10000,"5%",IF(G6>=5000,"2%","0%")))) -> 0% | L6: =IF(OR(G6>=5000,H6>=50),"YES","NO") -> NO
A7: 6 | B7: South | C7: Printer | D7: 105 | E7: Aman Bose | F7: Jun | G7: 6935 | H7: 56 | I7: =G7*H7 -> 388360 | J7: 46117 | K7: =IF(G7>=50000,"15%",IF(G7>=25000,"10%",IF(G7>=10000,"5%",IF(G7>=5000,"2%","0%")))) -> 2% | L7: =IF(OR(G7>=5000,H7>=50),"YES","NO") -> YES
A8: 7 | B8: East | C8: Monitor | D8: 102 | E8: Rahul Desai | F8: Jan | G8: 11209 | H8: 50 | I8: =G8*H8 -> 560450 | J8: 46189 | K8: =IF(G8>=50000,"15%",IF(G8>=25000,"10%",IF(G8>=10000,"5%",IF(G8>=5000,"2%","0%")))) -> 5% | L8: =IF(OR(G8>=5000,H8>=50),"YES","NO") -> YES
A9: 8 | B9: North | C9: Laptop | D9: 101 | E9: Aman Bose | F9: Feb | G9: 54973 | H9: 57 | I9: =G9*H9 -> 3133461 | J9: 46114 | K9: =IF(G9>=50000,"15%",IF(G9>=25000,"10%",IF(G9>=10000,"5%",IF(G9>=5000,"2%","0%")))) -> 15% | L9: =IF(OR(G9>=5000,H9>=50),"YES","NO") -> YES
A10: 9 | B10: South | C10: Printer | D10: 105 | E10: Sonal Kapoor | F10: Mar | G10: 6822 | H10: 6 | I10: =G10*H10 -> 40932 | J10: 46078 | K10: =IF(G10>=50000,"15%",IF(G10>=25000,"10%",IF(G10>=10000,"5%",IF(G10>=5000,"2%","0%")))) -> 2% | L10: =IF(OR(G10>=5000,H10>=50),"YES","NO") -> YES
A11: 10 | B11: South | C11: Monitor | D11: 102 | E11: Neha Kulkarni | F11: Apr | G11: 11702 | H11: 31 | I11: =G11*H11 -> 362762 | J11: 46159 | K11: =IF(G11>=50000,"15%",IF(G11>=25000,"10%",IF(G11>=10000,"5%",IF(G11>=5000,"2%","0%")))) -> 5% | L11: =IF(OR(G11>=5000,H11>=50),"YES","NO") -> YES
A12: 11 | B12: West | C12: Monitor | D12: 102 | E12: Neha Kulkarni | F12: May | G12: 12804 | H12: 35 | I12: =G12*H12 -> 448140 | J12: 46155 | K12: =IF(G12>=50000,"15%",IF(G12>=25000,"10%",IF(G12>=10000,"5%",IF(G12>=5000,"2%","0%")))) -> 5% | L12: =IF(OR(G12>=5000,H12>=50),"YES","NO") -> YES
A13: 12 | B13: East | C13: Mouse | D13: 104 | E13: Rahul Desai | F13: Jun | G13: 614 | H13: 29 | I13: =G13*H13 -> 17806 | J13: 46120 | K13: =IF(G13>=50000,"15%",IF(G13>=25000,"10%",IF(G13>=10000,"5%",IF(G13>=5000,"2%","0%")))) -> 0% | L13: =IF(OR(G13>=5000,H13>=50),"YES","NO") -> NO

Sheet Employee Data
A1: Employee ID | B1: Name | C1: Department | D1: Salary | E1: Joining Date | F1: Salary (Round) | G1: Salary (Ceiling) | H1: Salary (Floor) | I1: Days Since Joining
A2: 1 | B2: Nikhil Bhatt | C2: Sales | D2: 41649.48 | E2: 42295 | F2: =ROUND(D2,0) -> 41649 | G2: =CEILING(D2,100) -> 41700 | H2: =FLOOR(D2,100) -> 41600 | I2: =_xlfn.DAYS(TODAY(), E2) -> 3974
A3: 2 | B3: Pooja Menon | C3: Marketing | D3: 51116.54 | E3: 43103 | F3: =ROUND(D3,0) -> 51117 | G3: =CEILING(D3,100) -> 51200 | H3: =FLOOR(D3,100) -> 51100 | I3: =_xlfn.DAYS(TODAY(), E3) -> 3166
A4: 3 | B4: Sameer Khan | C4: Finance | D4: 78346.93 | E4: 42097 | F4: =ROUND(D4,0) -> 78347 | G4: =CEILING(D4,100) -> 78400 | H4: =FLOOR(D4,100) -> 78300 | I4: =_xlfn.DAYS(TODAY(), E4) -> 4172
A5: 4 | B5: Ritu Chawla | C5: HR | D5: 89608.94 | E5: 43878 | F5: =ROUND(D5,0) -> 89609 | G5: =CEILING(D5,100) -> 89700 | H5: =FLOOR(D5,100) -> 89600 | I5: =_xlfn.DAYS(TODAY(), E5) -> 2391
A6: 5 | B6: Devansh Rao | C6: IT | D6: 51566.26 | E6: 44669 | F6: =ROUND(D6,0) -> 51566 | G6: =CEILING(D6,100) -> 51600 | H6: =FLOOR(D6,100) -> 51500 | I6: =_xlfn.DAYS(TODAY(), E6) -> 1600
A7: 6 | B7: Kavya Pillai | C7: Sales | D7: 45541.78 | E7: 45581 | F7: =ROUND(D7,0) -> 45542 | G7: =CEILING(D7,100) -> 45600 | H7: =FLOOR(D7,100) -> 45500 | I7: =_xlfn.DAYS(TODAY(), E7) -> 688
A8: 7 | B8: Yash Trivedi | C8: Marketing | D8: 51850.84 | E8: 44749 | F8: =ROUND(D8,0) -> 51851 | G8: =CEILING(D8,100) -> 51900 | H8: =FLOOR(D8,100) -> 51800 | I8: =_xlfn.DAYS(TODAY(), E8) -> 1520
A9: 8 | B9: Alisha Dutta | C9: Finance | D9: 43376.57 | E9: 44361 | F9: =ROUND(D9,0) -> 43377 | G9: =CEILING(D9,100) -> 43400 | H9: =FLOOR(D9,100) -> 43300 | I9: =_xlfn.DAYS(TODAY(), E9) -> 1908
A10: 9 | B10: Tirth Donga | C10: HR | D10: 61432.83 | E10: 42329 | F10: =ROUND(D10,0) -> 61433 | G10: =CEILING(D10,100) -> 61500 | H10: =FLOOR(D10,100) -> 61400 | I10: =_xlfn.DAYS(TODAY(), E10) -> 3940
A11: 10 | B11: Virat Patel | C11: IT | D11: 94097.42 | E11: 42382 | F11: =ROUND(D11,0) -> 94097 | G11: =CEILING(D11,100) -> 94100 | H11: =FLOOR(D11,100) -> 94000 | I11: =_xlfn.DAYS(TODAY(), E11) -> 3887

Sheet Dashboard
A1: Count Math > 50: | B1: =COUNTIFS('Students grade'!D2:D13, ">50") -> 12 | D1: Student ID Lookup: | E1: 3 | G1: Range Reference: | H1: 'Sales Data'!I2:I13
A2: Avg Score for > 60: | B2: =AVERAGEIFS('Students grade'!F2:F13, 'Students grade'!F2:F13, ">60") -> 80.45 | D2: VLOOKUP Name: | E2: =VLOOKUP(E1, 'Students grade'!$A$2:$B$13, 2, FALSE) -> Meera Kapoor | G2: INDIRECT Sum: | H2: =SUM(INDIRECT(H1)) -> 10461802
A3: Sum Sales (North Laptop): | B3: =SUMIFS('Sales Data'!I2:I13, 'Sales Data'!B2:B13, "North", 'Sales Data'!C2:C13, "Laptop") -> 8599081
D4: Employee ID Lookup: | E4: 2 | G4: Last N Sales: | H4: 3
A5: Top Students (FILTER): | D5: INDEX/MATCH Dept: | E5: =INDEX('Employee Data'!C2:C11, MATCH(E4, 'Employee Data'!A2:A11, 0)) -> Marketing | G5: OFFSET Trend: | H5: =SUM(OFFSET('Sales Data'!I13, -(H4-1), 0, H4, 1)) -> 828708
A6: {=_xlfn._xlws.FILTER('Students grade'!A2:B13,'Students grade'!D2:D13>80)} -> 1 | B6: Ishita Rathod | D6: XLOOKUP Salary: | E6: =_xlfn.XLOOKUP(E4, 'Employee Data'!A2:A11, 'Employee Data'!D2:D11, "Not Found") -> 51116.54
A7: 2 | B7: Ishaan Solanki
A8: 3 | B8: Meera Kapoor | D8: Product Search: | E8: Laptop
A9: 4 | B9: Ritika Bhatt | D9: XMATCH Position: | E9: =_xlfn.XMATCH(E8, 'Sales Data'!C2:C13) -> 2
A10: 7 | B10: Tanvi Nair
A11: 10 | B11: Sneha Deshmukh | D11: Product Code: | E11: 101
D12: Price (VLOOKUP): | E12: =VLOOKUP(E11, 'Sales Data'!$D$2:$G$13, 4, FALSE) -> 53252
D14: Salesperson: | E14: Aman Bose
D15: Month: | E15: Apr
D16: Sales Amount: | E16: {=INDEX('Sales Data'!$I$2:$I$13, MATCH(E14&E15, 'Sales Data'!$E$2:$E$13&'Sales Data'!$F$2:$F$13, 0))} -> 3282288
D18: Salesperson (XLOOKUP): | E18: Sonal Kapoor
D19: Performance Found: | E19: =_xlfn.XLOOKUP(E18, 'Sales Data'!$E$2:$E$13, 'Sales Data'!$I$2:$I$13, "Not Found") -> 10116
